confindr_src/__init__.py
confindr_src/confindr.py
confindr_src/create_genus_specific_db.py
confindr_src/database_setup.py
confindr_src/methods.py
confindr_src/wrappers/__init__.py
confindr_src/wrappers/bbtools.py
confindr_src/wrappers/mash.py
confindr-0.8.2.dist-info/LICENSE
confindr-0.8.2.dist-info/METADATA
confindr-0.8.2.dist-info/WHEEL
confindr-0.8.2.dist-info/entry_points.txt
confindr-0.8.2.dist-info/top_level.txt
confindr-0.8.2.dist-info/RECORD
